<mxfile host="app.diagrams.net" agent="Mozilla/5.0 (Windows NT 10.0; Win64; x64) AppleWebKit/537.36 (KHTML, like Gecko) Chrome/122.0.0.0 Safari/537.36 Edg/122.0.0.0">
  <diagram id="R2lEEEUBdFMjLlhIrx00" name="Page-1">
    <mxGraphModel dx="1480" dy="785" grid="1" gridSize="10" guides="1" tooltips="1" connect="1" arrows="1" fold="1" page="1" pageScale="1" pageWidth="850" pageHeight="1100" math="0" shadow="0" extFonts="Permanent Marker^https://fonts.googleapis.com/css?family=Permanent+Marker">
      <root>
        <mxCell id="0" />
        <mxCell id="1" parent="0" />
        <mxCell id="KqVh3688gUcW49LKLbx4-1" parent="1" style="shape=table;startSize=30;container=1;collapsible=1;childLayout=tableLayout;fixedRows=1;rowLines=0;fontStyle=1;align=center;resizeLast=1;html=1;" value="User" vertex="1">
          <mxGeometry height="165" width="200" x="20" y="55" as="geometry" />
        </mxCell>
        <mxCell id="KqVh3688gUcW49LKLbx4-2" parent="KqVh3688gUcW49LKLbx4-1" style="shape=tableRow;horizontal=0;startSize=0;swimlaneHead=0;swimlaneBody=0;fillColor=none;collapsible=0;dropTarget=0;points=[[0,0.5],[1,0.5]];portConstraint=eastwest;top=0;left=0;right=0;bottom=1;" value="" vertex="1">
          <mxGeometry height="35" width="200" y="30" as="geometry" />
        </mxCell>
        <mxCell id="KqVh3688gUcW49LKLbx4-3" parent="KqVh3688gUcW49LKLbx4-2" style="shape=partialRectangle;connectable=0;fillColor=none;top=0;left=0;bottom=0;right=0;fontStyle=1;overflow=hidden;whiteSpace=wrap;html=1;" value="PK" vertex="1">
          <mxGeometry height="35" width="30" as="geometry">
            <mxRectangle height="35" width="30" as="alternateBounds" />
          </mxGeometry>
        </mxCell>
        <mxCell id="KqVh3688gUcW49LKLbx4-4" parent="KqVh3688gUcW49LKLbx4-2" style="shape=partialRectangle;connectable=0;fillColor=none;top=0;left=0;bottom=0;right=0;align=left;spacingLeft=6;fontStyle=5;overflow=hidden;whiteSpace=wrap;html=1;" value="&lt;span style=&quot;text-wrap: nowrap;&quot;&gt;user_id&amp;nbsp;int NOT NULL&lt;/span&gt;" vertex="1">
          <mxGeometry height="35" width="170" x="30" as="geometry">
            <mxRectangle height="35" width="170" as="alternateBounds" />
          </mxGeometry>
        </mxCell>
        <mxCell id="KqVh3688gUcW49LKLbx4-5" parent="KqVh3688gUcW49LKLbx4-1" style="shape=tableRow;horizontal=0;startSize=0;swimlaneHead=0;swimlaneBody=0;fillColor=none;collapsible=0;dropTarget=0;points=[[0,0.5],[1,0.5]];portConstraint=eastwest;top=0;left=0;right=0;bottom=0;" value="" vertex="1">
          <mxGeometry height="25" width="200" y="65" as="geometry" />
        </mxCell>
        <mxCell id="KqVh3688gUcW49LKLbx4-6" parent="KqVh3688gUcW49LKLbx4-5" style="shape=partialRectangle;connectable=0;fillColor=none;top=0;left=0;bottom=0;right=0;editable=1;overflow=hidden;whiteSpace=wrap;html=1;" value="" vertex="1">
          <mxGeometry height="25" width="30" as="geometry">
            <mxRectangle height="25" width="30" as="alternateBounds" />
          </mxGeometry>
        </mxCell>
        <mxCell id="KqVh3688gUcW49LKLbx4-7" parent="KqVh3688gUcW49LKLbx4-5" style="shape=partialRectangle;connectable=0;fillColor=none;top=0;left=0;bottom=0;right=0;align=left;spacingLeft=6;overflow=hidden;whiteSpace=wrap;html=1;" value="&lt;span style=&quot;text-wrap: nowrap;&quot;&gt;name&amp;nbsp;&lt;/span&gt;&lt;span style=&quot;white-space: nowrap;&quot;&gt;varchar&lt;/span&gt;" vertex="1">
          <mxGeometry height="25" width="170" x="30" as="geometry">
            <mxRectangle height="25" width="170" as="alternateBounds" />
          </mxGeometry>
        </mxCell>
        <mxCell id="KqVh3688gUcW49LKLbx4-8" parent="KqVh3688gUcW49LKLbx4-1" style="shape=tableRow;horizontal=0;startSize=0;swimlaneHead=0;swimlaneBody=0;fillColor=none;collapsible=0;dropTarget=0;points=[[0,0.5],[1,0.5]];portConstraint=eastwest;top=0;left=0;right=0;bottom=0;" value="" vertex="1">
          <mxGeometry height="30" width="200" y="90" as="geometry" />
        </mxCell>
        <mxCell id="KqVh3688gUcW49LKLbx4-9" parent="KqVh3688gUcW49LKLbx4-8" style="shape=partialRectangle;connectable=0;fillColor=none;top=0;left=0;bottom=0;right=0;editable=1;overflow=hidden;whiteSpace=wrap;html=1;" value="" vertex="1">
          <mxGeometry height="30" width="30" as="geometry">
            <mxRectangle height="30" width="30" as="alternateBounds" />
          </mxGeometry>
        </mxCell>
        <mxCell id="KqVh3688gUcW49LKLbx4-10" parent="KqVh3688gUcW49LKLbx4-8" style="shape=partialRectangle;connectable=0;fillColor=none;top=0;left=0;bottom=0;right=0;align=left;spacingLeft=6;overflow=hidden;whiteSpace=wrap;html=1;" value="&lt;span style=&quot;text-wrap: nowrap;&quot;&gt;birthday date&lt;/span&gt;" vertex="1">
          <mxGeometry height="30" width="170" x="30" as="geometry">
            <mxRectangle height="30" width="170" as="alternateBounds" />
          </mxGeometry>
        </mxCell>
        <mxCell id="qyUYULa52Rrzh8f9O8Ic-1" parent="KqVh3688gUcW49LKLbx4-1" style="shape=tableRow;horizontal=0;startSize=0;swimlaneHead=0;swimlaneBody=0;fillColor=none;collapsible=0;dropTarget=0;points=[[0,0.5],[1,0.5]];portConstraint=eastwest;top=0;left=0;right=0;bottom=0;" value="" vertex="1">
          <mxGeometry height="30" width="200" y="120" as="geometry" />
        </mxCell>
        <mxCell id="qyUYULa52Rrzh8f9O8Ic-2" parent="qyUYULa52Rrzh8f9O8Ic-1" style="shape=partialRectangle;connectable=0;fillColor=none;top=0;left=0;bottom=0;right=0;editable=1;overflow=hidden;whiteSpace=wrap;html=1;" value="" vertex="1">
          <mxGeometry height="30" width="30" as="geometry">
            <mxRectangle height="30" width="30" as="alternateBounds" />
          </mxGeometry>
        </mxCell>
        <mxCell id="qyUYULa52Rrzh8f9O8Ic-3" parent="qyUYULa52Rrzh8f9O8Ic-1" style="shape=partialRectangle;connectable=0;fillColor=none;top=0;left=0;bottom=0;right=0;align=left;spacingLeft=6;overflow=hidden;whiteSpace=wrap;html=1;" value="&lt;span style=&quot;text-wrap: nowrap;&quot;&gt;address varchar&lt;/span&gt;" vertex="1">
          <mxGeometry height="30" width="170" x="30" as="geometry">
            <mxRectangle height="30" width="170" as="alternateBounds" />
          </mxGeometry>
        </mxCell>
        <mxCell id="qyUYULa52Rrzh8f9O8Ic-5" parent="1" style="shape=table;startSize=30;container=1;collapsible=1;childLayout=tableLayout;fixedRows=1;rowLines=0;fontStyle=1;align=center;resizeLast=1;html=1;" value="Business Owner" vertex="1">
          <mxGeometry height="140" width="200" x="280" y="55" as="geometry" />
        </mxCell>
        <mxCell id="qyUYULa52Rrzh8f9O8Ic-6" parent="qyUYULa52Rrzh8f9O8Ic-5" style="shape=tableRow;horizontal=0;startSize=0;swimlaneHead=0;swimlaneBody=0;fillColor=none;collapsible=0;dropTarget=0;points=[[0,0.5],[1,0.5]];portConstraint=eastwest;top=0;left=0;right=0;bottom=1;" value="" vertex="1">
          <mxGeometry height="35" width="200" y="30" as="geometry" />
        </mxCell>
        <mxCell id="qyUYULa52Rrzh8f9O8Ic-7" parent="qyUYULa52Rrzh8f9O8Ic-6" style="shape=partialRectangle;connectable=0;fillColor=none;top=0;left=0;bottom=0;right=0;fontStyle=1;overflow=hidden;whiteSpace=wrap;html=1;" value="PK" vertex="1">
          <mxGeometry height="35" width="30" as="geometry">
            <mxRectangle height="35" width="30" as="alternateBounds" />
          </mxGeometry>
        </mxCell>
        <mxCell id="qyUYULa52Rrzh8f9O8Ic-8" parent="qyUYULa52Rrzh8f9O8Ic-6" style="shape=partialRectangle;connectable=0;fillColor=none;top=0;left=0;bottom=0;right=0;align=left;spacingLeft=6;fontStyle=5;overflow=hidden;whiteSpace=wrap;html=1;" value="&lt;span style=&quot;text-wrap: nowrap;&quot;&gt;owner_id int NOT NULL&lt;/span&gt;" vertex="1">
          <mxGeometry height="35" width="170" x="30" as="geometry">
            <mxRectangle height="35" width="170" as="alternateBounds" />
          </mxGeometry>
        </mxCell>
        <mxCell id="qyUYULa52Rrzh8f9O8Ic-9" parent="qyUYULa52Rrzh8f9O8Ic-5" style="shape=tableRow;horizontal=0;startSize=0;swimlaneHead=0;swimlaneBody=0;fillColor=none;collapsible=0;dropTarget=0;points=[[0,0.5],[1,0.5]];portConstraint=eastwest;top=0;left=0;right=0;bottom=0;" value="" vertex="1">
          <mxGeometry height="30" width="200" y="65" as="geometry" />
        </mxCell>
        <mxCell id="qyUYULa52Rrzh8f9O8Ic-10" parent="qyUYULa52Rrzh8f9O8Ic-9" style="shape=partialRectangle;connectable=0;fillColor=none;top=0;left=0;bottom=0;right=0;editable=1;overflow=hidden;whiteSpace=wrap;html=1;" value="FK" vertex="1">
          <mxGeometry height="30" width="30" as="geometry">
            <mxRectangle height="30" width="30" as="alternateBounds" />
          </mxGeometry>
        </mxCell>
        <mxCell id="qyUYULa52Rrzh8f9O8Ic-11" parent="qyUYULa52Rrzh8f9O8Ic-9" style="shape=partialRectangle;connectable=0;fillColor=none;top=0;left=0;bottom=0;right=0;align=left;spacingLeft=6;overflow=hidden;whiteSpace=wrap;html=1;" value="&lt;span style=&quot;text-wrap-mode: nowrap;&quot;&gt;user_id int&lt;/span&gt;" vertex="1">
          <mxGeometry height="30" width="170" x="30" as="geometry">
            <mxRectangle height="30" width="170" as="alternateBounds" />
          </mxGeometry>
        </mxCell>
        <mxCell id="qyUYULa52Rrzh8f9O8Ic-15" parent="qyUYULa52Rrzh8f9O8Ic-5" style="shape=tableRow;horizontal=0;startSize=0;swimlaneHead=0;swimlaneBody=0;fillColor=none;collapsible=0;dropTarget=0;points=[[0,0.5],[1,0.5]];portConstraint=eastwest;top=0;left=0;right=0;bottom=0;" value="" vertex="1">
          <mxGeometry height="30" width="200" y="95" as="geometry" />
        </mxCell>
        <mxCell id="qyUYULa52Rrzh8f9O8Ic-16" parent="qyUYULa52Rrzh8f9O8Ic-15" style="shape=partialRectangle;connectable=0;fillColor=none;top=0;left=0;bottom=0;right=0;editable=1;overflow=hidden;whiteSpace=wrap;html=1;" value="" vertex="1">
          <mxGeometry height="30" width="30" as="geometry">
            <mxRectangle height="30" width="30" as="alternateBounds" />
          </mxGeometry>
        </mxCell>
        <mxCell id="qyUYULa52Rrzh8f9O8Ic-17" parent="qyUYULa52Rrzh8f9O8Ic-15" style="shape=partialRectangle;connectable=0;fillColor=none;top=0;left=0;bottom=0;right=0;align=left;spacingLeft=6;overflow=hidden;whiteSpace=wrap;html=1;" value="&lt;span style=&quot;text-wrap: nowrap;&quot;&gt;linkedin varchar&lt;/span&gt;" vertex="1">
          <mxGeometry height="30" width="170" x="30" as="geometry">
            <mxRectangle height="30" width="170" as="alternateBounds" />
          </mxGeometry>
        </mxCell>
        <mxCell id="qyUYULa52Rrzh8f9O8Ic-18" parent="1" style="shape=table;startSize=30;container=1;collapsible=1;childLayout=tableLayout;fixedRows=1;rowLines=0;fontStyle=1;align=center;resizeLast=1;html=1;" value="Hungry Customer" vertex="1">
          <mxGeometry height="140" width="200" x="290" y="220" as="geometry" />
        </mxCell>
        <mxCell id="qyUYULa52Rrzh8f9O8Ic-19" parent="qyUYULa52Rrzh8f9O8Ic-18" style="shape=tableRow;horizontal=0;startSize=0;swimlaneHead=0;swimlaneBody=0;fillColor=none;collapsible=0;dropTarget=0;points=[[0,0.5],[1,0.5]];portConstraint=eastwest;top=0;left=0;right=0;bottom=1;" value="" vertex="1">
          <mxGeometry height="35" width="200" y="30" as="geometry" />
        </mxCell>
        <mxCell id="qyUYULa52Rrzh8f9O8Ic-20" parent="qyUYULa52Rrzh8f9O8Ic-19" style="shape=partialRectangle;connectable=0;fillColor=none;top=0;left=0;bottom=0;right=0;fontStyle=1;overflow=hidden;whiteSpace=wrap;html=1;" value="PK" vertex="1">
          <mxGeometry height="35" width="30" as="geometry">
            <mxRectangle height="35" width="30" as="alternateBounds" />
          </mxGeometry>
        </mxCell>
        <mxCell id="qyUYULa52Rrzh8f9O8Ic-21" parent="qyUYULa52Rrzh8f9O8Ic-19" style="shape=partialRectangle;connectable=0;fillColor=none;top=0;left=0;bottom=0;right=0;align=left;spacingLeft=6;fontStyle=5;overflow=hidden;whiteSpace=wrap;html=1;" value="&lt;span style=&quot;text-wrap: nowrap;&quot;&gt;customer_id int NOT NULL&lt;/span&gt;" vertex="1">
          <mxGeometry height="35" width="170" x="30" as="geometry">
            <mxRectangle height="35" width="170" as="alternateBounds" />
          </mxGeometry>
        </mxCell>
        <mxCell id="qyUYULa52Rrzh8f9O8Ic-22" parent="qyUYULa52Rrzh8f9O8Ic-18" style="shape=tableRow;horizontal=0;startSize=0;swimlaneHead=0;swimlaneBody=0;fillColor=none;collapsible=0;dropTarget=0;points=[[0,0.5],[1,0.5]];portConstraint=eastwest;top=0;left=0;right=0;bottom=0;" value="" vertex="1">
          <mxGeometry height="30" width="200" y="65" as="geometry" />
        </mxCell>
        <mxCell id="qyUYULa52Rrzh8f9O8Ic-23" parent="qyUYULa52Rrzh8f9O8Ic-22" style="shape=partialRectangle;connectable=0;fillColor=none;top=0;left=0;bottom=0;right=0;editable=1;overflow=hidden;whiteSpace=wrap;html=1;" value="FK" vertex="1">
          <mxGeometry height="30" width="30" as="geometry">
            <mxRectangle height="30" width="30" as="alternateBounds" />
          </mxGeometry>
        </mxCell>
        <mxCell id="qyUYULa52Rrzh8f9O8Ic-24" parent="qyUYULa52Rrzh8f9O8Ic-22" style="shape=partialRectangle;connectable=0;fillColor=none;top=0;left=0;bottom=0;right=0;align=left;spacingLeft=6;overflow=hidden;whiteSpace=wrap;html=1;" value="&lt;span style=&quot;text-wrap-mode: nowrap;&quot;&gt;user_id int&lt;/span&gt;" vertex="1">
          <mxGeometry height="30" width="170" x="30" as="geometry">
            <mxRectangle height="30" width="170" as="alternateBounds" />
          </mxGeometry>
        </mxCell>
        <mxCell id="qyUYULa52Rrzh8f9O8Ic-25" parent="qyUYULa52Rrzh8f9O8Ic-18" style="shape=tableRow;horizontal=0;startSize=0;swimlaneHead=0;swimlaneBody=0;fillColor=none;collapsible=0;dropTarget=0;points=[[0,0.5],[1,0.5]];portConstraint=eastwest;top=0;left=0;right=0;bottom=0;" value="" vertex="1">
          <mxGeometry height="30" width="200" y="95" as="geometry" />
        </mxCell>
        <mxCell id="qyUYULa52Rrzh8f9O8Ic-26" parent="qyUYULa52Rrzh8f9O8Ic-25" style="shape=partialRectangle;connectable=0;fillColor=none;top=0;left=0;bottom=0;right=0;editable=1;overflow=hidden;whiteSpace=wrap;html=1;" value="" vertex="1">
          <mxGeometry height="30" width="30" as="geometry">
            <mxRectangle height="30" width="30" as="alternateBounds" />
          </mxGeometry>
        </mxCell>
        <mxCell id="qyUYULa52Rrzh8f9O8Ic-27" parent="qyUYULa52Rrzh8f9O8Ic-25" style="shape=partialRectangle;connectable=0;fillColor=none;top=0;left=0;bottom=0;right=0;align=left;spacingLeft=6;overflow=hidden;whiteSpace=wrap;html=1;" value="&lt;span style=&quot;text-wrap: nowrap;&quot;&gt;delivery_address varchar&lt;/span&gt;" vertex="1">
          <mxGeometry height="30" width="170" x="30" as="geometry">
            <mxRectangle height="30" width="170" as="alternateBounds" />
          </mxGeometry>
        </mxCell>
        <mxCell id="qyUYULa52Rrzh8f9O8Ic-28" parent="1" style="shape=table;startSize=30;container=1;collapsible=1;childLayout=tableLayout;fixedRows=1;rowLines=0;fontStyle=1;align=center;resizeLast=1;html=1;" value="Entertainer" vertex="1">
          <mxGeometry height="200" width="200" x="20" y="260" as="geometry" />
        </mxCell>
        <mxCell id="qyUYULa52Rrzh8f9O8Ic-29" parent="qyUYULa52Rrzh8f9O8Ic-28" style="shape=tableRow;horizontal=0;startSize=0;swimlaneHead=0;swimlaneBody=0;fillColor=none;collapsible=0;dropTarget=0;points=[[0,0.5],[1,0.5]];portConstraint=eastwest;top=0;left=0;right=0;bottom=1;" value="" vertex="1">
          <mxGeometry height="35" width="200" y="30" as="geometry" />
        </mxCell>
        <mxCell id="qyUYULa52Rrzh8f9O8Ic-30" parent="qyUYULa52Rrzh8f9O8Ic-29" style="shape=partialRectangle;connectable=0;fillColor=none;top=0;left=0;bottom=0;right=0;fontStyle=1;overflow=hidden;whiteSpace=wrap;html=1;" value="PK" vertex="1">
          <mxGeometry height="35" width="30" as="geometry">
            <mxRectangle height="35" width="30" as="alternateBounds" />
          </mxGeometry>
        </mxCell>
        <mxCell id="qyUYULa52Rrzh8f9O8Ic-31" parent="qyUYULa52Rrzh8f9O8Ic-29" style="shape=partialRectangle;connectable=0;fillColor=none;top=0;left=0;bottom=0;right=0;align=left;spacingLeft=6;fontStyle=5;overflow=hidden;whiteSpace=wrap;html=1;" value="&lt;span style=&quot;text-wrap: nowrap;&quot;&gt;entertainer_id int NOT NULL&lt;/span&gt;" vertex="1">
          <mxGeometry height="35" width="170" x="30" as="geometry">
            <mxRectangle height="35" width="170" as="alternateBounds" />
          </mxGeometry>
        </mxCell>
        <mxCell id="qyUYULa52Rrzh8f9O8Ic-32" parent="qyUYULa52Rrzh8f9O8Ic-28" style="shape=tableRow;horizontal=0;startSize=0;swimlaneHead=0;swimlaneBody=0;fillColor=none;collapsible=0;dropTarget=0;points=[[0,0.5],[1,0.5]];portConstraint=eastwest;top=0;left=0;right=0;bottom=0;" value="" vertex="1">
          <mxGeometry height="30" width="200" y="65" as="geometry" />
        </mxCell>
        <mxCell id="qyUYULa52Rrzh8f9O8Ic-33" parent="qyUYULa52Rrzh8f9O8Ic-32" style="shape=partialRectangle;connectable=0;fillColor=none;top=0;left=0;bottom=0;right=0;editable=1;overflow=hidden;whiteSpace=wrap;html=1;" value="FK" vertex="1">
          <mxGeometry height="30" width="30" as="geometry">
            <mxRectangle height="30" width="30" as="alternateBounds" />
          </mxGeometry>
        </mxCell>
        <mxCell id="qyUYULa52Rrzh8f9O8Ic-34" parent="qyUYULa52Rrzh8f9O8Ic-32" style="shape=partialRectangle;connectable=0;fillColor=none;top=0;left=0;bottom=0;right=0;align=left;spacingLeft=6;overflow=hidden;whiteSpace=wrap;html=1;" value="&lt;span style=&quot;text-wrap-mode: nowrap;&quot;&gt;user_id int&lt;/span&gt;" vertex="1">
          <mxGeometry height="30" width="170" x="30" as="geometry">
            <mxRectangle height="30" width="170" as="alternateBounds" />
          </mxGeometry>
        </mxCell>
        <mxCell id="qyUYULa52Rrzh8f9O8Ic-35" parent="qyUYULa52Rrzh8f9O8Ic-28" style="shape=tableRow;horizontal=0;startSize=0;swimlaneHead=0;swimlaneBody=0;fillColor=none;collapsible=0;dropTarget=0;points=[[0,0.5],[1,0.5]];portConstraint=eastwest;top=0;left=0;right=0;bottom=0;" value="" vertex="1">
          <mxGeometry height="30" width="200" y="95" as="geometry" />
        </mxCell>
        <mxCell id="qyUYULa52Rrzh8f9O8Ic-36" parent="qyUYULa52Rrzh8f9O8Ic-35" style="shape=partialRectangle;connectable=0;fillColor=none;top=0;left=0;bottom=0;right=0;editable=1;overflow=hidden;whiteSpace=wrap;html=1;" value="" vertex="1">
          <mxGeometry height="30" width="30" as="geometry">
            <mxRectangle height="30" width="30" as="alternateBounds" />
          </mxGeometry>
        </mxCell>
        <mxCell id="qyUYULa52Rrzh8f9O8Ic-37" parent="qyUYULa52Rrzh8f9O8Ic-35" style="shape=partialRectangle;connectable=0;fillColor=none;top=0;left=0;bottom=0;right=0;align=left;spacingLeft=6;overflow=hidden;whiteSpace=wrap;html=1;" value="&lt;span style=&quot;text-wrap: nowrap;&quot;&gt;stage_name varchar&lt;/span&gt;" vertex="1">
          <mxGeometry height="30" width="170" x="30" as="geometry">
            <mxRectangle height="30" width="170" as="alternateBounds" />
          </mxGeometry>
        </mxCell>
        <mxCell id="qyUYULa52Rrzh8f9O8Ic-39" parent="qyUYULa52Rrzh8f9O8Ic-28" style="shape=tableRow;horizontal=0;startSize=0;swimlaneHead=0;swimlaneBody=0;fillColor=none;collapsible=0;dropTarget=0;points=[[0,0.5],[1,0.5]];portConstraint=eastwest;top=0;left=0;right=0;bottom=0;" value="" vertex="1">
          <mxGeometry height="30" width="200" y="125" as="geometry" />
        </mxCell>
        <mxCell id="qyUYULa52Rrzh8f9O8Ic-40" parent="qyUYULa52Rrzh8f9O8Ic-39" style="shape=partialRectangle;connectable=0;fillColor=none;top=0;left=0;bottom=0;right=0;editable=1;overflow=hidden;whiteSpace=wrap;html=1;" value="" vertex="1">
          <mxGeometry height="30" width="30" as="geometry">
            <mxRectangle height="30" width="30" as="alternateBounds" />
          </mxGeometry>
        </mxCell>
        <mxCell id="qyUYULa52Rrzh8f9O8Ic-41" parent="qyUYULa52Rrzh8f9O8Ic-39" style="shape=partialRectangle;connectable=0;fillColor=none;top=0;left=0;bottom=0;right=0;align=left;spacingLeft=6;overflow=hidden;whiteSpace=wrap;html=1;" value="&lt;span style=&quot;text-wrap: nowrap;&quot;&gt;bio text&lt;/span&gt;" vertex="1">
          <mxGeometry height="30" width="170" x="30" as="geometry">
            <mxRectangle height="30" width="170" as="alternateBounds" />
          </mxGeometry>
        </mxCell>
        <mxCell id="qyUYULa52Rrzh8f9O8Ic-42" parent="qyUYULa52Rrzh8f9O8Ic-28" style="shape=tableRow;horizontal=0;startSize=0;swimlaneHead=0;swimlaneBody=0;fillColor=none;collapsible=0;dropTarget=0;points=[[0,0.5],[1,0.5]];portConstraint=eastwest;top=0;left=0;right=0;bottom=0;" value="" vertex="1">
          <mxGeometry height="30" width="200" y="155" as="geometry" />
        </mxCell>
        <mxCell id="qyUYULa52Rrzh8f9O8Ic-43" parent="qyUYULa52Rrzh8f9O8Ic-42" style="shape=partialRectangle;connectable=0;fillColor=none;top=0;left=0;bottom=0;right=0;editable=1;overflow=hidden;whiteSpace=wrap;html=1;" value="" vertex="1">
          <mxGeometry height="30" width="30" as="geometry">
            <mxRectangle height="30" width="30" as="alternateBounds" />
          </mxGeometry>
        </mxCell>
        <mxCell id="qyUYULa52Rrzh8f9O8Ic-44" parent="qyUYULa52Rrzh8f9O8Ic-42" style="shape=partialRectangle;connectable=0;fillColor=none;top=0;left=0;bottom=0;right=0;align=left;spacingLeft=6;overflow=hidden;whiteSpace=wrap;html=1;" value="&lt;span style=&quot;text-wrap: nowrap;&quot;&gt;price_per_30min int&lt;/span&gt;" vertex="1">
          <mxGeometry height="30" width="170" x="30" as="geometry">
            <mxRectangle height="30" width="170" as="alternateBounds" />
          </mxGeometry>
        </mxCell>
        <mxCell id="qyUYULa52Rrzh8f9O8Ic-45" parent="1" style="shape=table;startSize=30;container=1;collapsible=1;childLayout=tableLayout;fixedRows=1;rowLines=0;fontStyle=1;align=center;resizeLast=1;html=1;" value="Pizza Resturant" vertex="1">
          <mxGeometry height="260" width="200" x="525" y="55" as="geometry" />
        </mxCell>
        <mxCell id="qyUYULa52Rrzh8f9O8Ic-46" parent="qyUYULa52Rrzh8f9O8Ic-45" style="shape=tableRow;horizontal=0;startSize=0;swimlaneHead=0;swimlaneBody=0;fillColor=none;collapsible=0;dropTarget=0;points=[[0,0.5],[1,0.5]];portConstraint=eastwest;top=0;left=0;right=0;bottom=1;" value="" vertex="1">
          <mxGeometry height="35" width="200" y="30" as="geometry" />
        </mxCell>
        <mxCell id="qyUYULa52Rrzh8f9O8Ic-47" parent="qyUYULa52Rrzh8f9O8Ic-46" style="shape=partialRectangle;connectable=0;fillColor=none;top=0;left=0;bottom=0;right=0;fontStyle=1;overflow=hidden;whiteSpace=wrap;html=1;" value="PK" vertex="1">
          <mxGeometry height="35" width="30" as="geometry">
            <mxRectangle height="35" width="30" as="alternateBounds" />
          </mxGeometry>
        </mxCell>
        <mxCell id="qyUYULa52Rrzh8f9O8Ic-48" parent="qyUYULa52Rrzh8f9O8Ic-46" style="shape=partialRectangle;connectable=0;fillColor=none;top=0;left=0;bottom=0;right=0;align=left;spacingLeft=6;fontStyle=5;overflow=hidden;whiteSpace=wrap;html=1;" value="&lt;span style=&quot;text-wrap: nowrap;&quot;&gt;resturant_id int NOT NULL&lt;/span&gt;" vertex="1">
          <mxGeometry height="35" width="170" x="30" as="geometry">
            <mxRectangle height="35" width="170" as="alternateBounds" />
          </mxGeometry>
        </mxCell>
        <mxCell id="qyUYULa52Rrzh8f9O8Ic-49" parent="qyUYULa52Rrzh8f9O8Ic-45" style="shape=tableRow;horizontal=0;startSize=0;swimlaneHead=0;swimlaneBody=0;fillColor=none;collapsible=0;dropTarget=0;points=[[0,0.5],[1,0.5]];portConstraint=eastwest;top=0;left=0;right=0;bottom=0;" value="" vertex="1">
          <mxGeometry height="30" width="200" y="65" as="geometry" />
        </mxCell>
        <mxCell id="qyUYULa52Rrzh8f9O8Ic-50" parent="qyUYULa52Rrzh8f9O8Ic-49" style="shape=partialRectangle;connectable=0;fillColor=none;top=0;left=0;bottom=0;right=0;editable=1;overflow=hidden;whiteSpace=wrap;html=1;" value="FK" vertex="1">
          <mxGeometry height="30" width="30" as="geometry">
            <mxRectangle height="30" width="30" as="alternateBounds" />
          </mxGeometry>
        </mxCell>
        <mxCell id="qyUYULa52Rrzh8f9O8Ic-51" parent="qyUYULa52Rrzh8f9O8Ic-49" style="shape=partialRectangle;connectable=0;fillColor=none;top=0;left=0;bottom=0;right=0;align=left;spacingLeft=6;overflow=hidden;whiteSpace=wrap;html=1;" value="&lt;span style=&quot;text-wrap-mode: nowrap;&quot;&gt;owner_id int&lt;/span&gt;" vertex="1">
          <mxGeometry height="30" width="170" x="30" as="geometry">
            <mxRectangle height="30" width="170" as="alternateBounds" />
          </mxGeometry>
        </mxCell>
        <mxCell id="qyUYULa52Rrzh8f9O8Ic-52" parent="qyUYULa52Rrzh8f9O8Ic-45" style="shape=tableRow;horizontal=0;startSize=0;swimlaneHead=0;swimlaneBody=0;fillColor=none;collapsible=0;dropTarget=0;points=[[0,0.5],[1,0.5]];portConstraint=eastwest;top=0;left=0;right=0;bottom=0;" value="" vertex="1">
          <mxGeometry height="30" width="200" y="95" as="geometry" />
        </mxCell>
        <mxCell id="qyUYULa52Rrzh8f9O8Ic-53" parent="qyUYULa52Rrzh8f9O8Ic-52" style="shape=partialRectangle;connectable=0;fillColor=none;top=0;left=0;bottom=0;right=0;editable=1;overflow=hidden;whiteSpace=wrap;html=1;" value="" vertex="1">
          <mxGeometry height="30" width="30" as="geometry">
            <mxRectangle height="30" width="30" as="alternateBounds" />
          </mxGeometry>
        </mxCell>
        <mxCell id="qyUYULa52Rrzh8f9O8Ic-54" parent="qyUYULa52Rrzh8f9O8Ic-52" style="shape=partialRectangle;connectable=0;fillColor=none;top=0;left=0;bottom=0;right=0;align=left;spacingLeft=6;overflow=hidden;whiteSpace=wrap;html=1;" value="&lt;span style=&quot;text-wrap: nowrap;&quot;&gt;zipcode varchar&lt;/span&gt;" vertex="1">
          <mxGeometry height="30" width="170" x="30" as="geometry">
            <mxRectangle height="30" width="170" as="alternateBounds" />
          </mxGeometry>
        </mxCell>
        <mxCell id="qyUYULa52Rrzh8f9O8Ic-61" parent="qyUYULa52Rrzh8f9O8Ic-45" style="shape=tableRow;horizontal=0;startSize=0;swimlaneHead=0;swimlaneBody=0;fillColor=none;collapsible=0;dropTarget=0;points=[[0,0.5],[1,0.5]];portConstraint=eastwest;top=0;left=0;right=0;bottom=0;" value="" vertex="1">
          <mxGeometry height="30" width="200" y="125" as="geometry" />
        </mxCell>
        <mxCell id="qyUYULa52Rrzh8f9O8Ic-62" parent="qyUYULa52Rrzh8f9O8Ic-61" style="shape=partialRectangle;connectable=0;fillColor=none;top=0;left=0;bottom=0;right=0;editable=1;overflow=hidden;whiteSpace=wrap;html=1;" value="" vertex="1">
          <mxGeometry height="30" width="30" as="geometry">
            <mxRectangle height="30" width="30" as="alternateBounds" />
          </mxGeometry>
        </mxCell>
        <mxCell id="qyUYULa52Rrzh8f9O8Ic-63" parent="qyUYULa52Rrzh8f9O8Ic-61" style="shape=partialRectangle;connectable=0;fillColor=none;top=0;left=0;bottom=0;right=0;align=left;spacingLeft=6;overflow=hidden;whiteSpace=wrap;html=1;" value="&lt;span style=&quot;text-wrap: nowrap;&quot;&gt;address varchar&lt;/span&gt;" vertex="1">
          <mxGeometry height="30" width="170" x="30" as="geometry">
            <mxRectangle height="30" width="170" as="alternateBounds" />
          </mxGeometry>
        </mxCell>
        <mxCell id="qyUYULa52Rrzh8f9O8Ic-77" parent="qyUYULa52Rrzh8f9O8Ic-45" style="shape=tableRow;horizontal=0;startSize=0;swimlaneHead=0;swimlaneBody=0;fillColor=none;collapsible=0;dropTarget=0;points=[[0,0.5],[1,0.5]];portConstraint=eastwest;top=0;left=0;right=0;bottom=0;" value="" vertex="1">
          <mxGeometry height="30" width="200" y="155" as="geometry" />
        </mxCell>
        <mxCell id="qyUYULa52Rrzh8f9O8Ic-78" parent="qyUYULa52Rrzh8f9O8Ic-77" style="shape=partialRectangle;connectable=0;fillColor=none;top=0;left=0;bottom=0;right=0;editable=1;overflow=hidden;whiteSpace=wrap;html=1;" value="" vertex="1">
          <mxGeometry height="30" width="30" as="geometry">
            <mxRectangle height="30" width="30" as="alternateBounds" />
          </mxGeometry>
        </mxCell>
        <mxCell id="qyUYULa52Rrzh8f9O8Ic-79" parent="qyUYULa52Rrzh8f9O8Ic-77" style="shape=partialRectangle;connectable=0;fillColor=none;top=0;left=0;bottom=0;right=0;align=left;spacingLeft=6;overflow=hidden;whiteSpace=wrap;html=1;" value="&lt;span style=&quot;text-wrap: nowrap;&quot;&gt;phone varchar&lt;/span&gt;" vertex="1">
          <mxGeometry height="30" width="170" x="30" as="geometry">
            <mxRectangle height="30" width="170" as="alternateBounds" />
          </mxGeometry>
        </mxCell>
        <mxCell id="qyUYULa52Rrzh8f9O8Ic-80" parent="qyUYULa52Rrzh8f9O8Ic-45" style="shape=tableRow;horizontal=0;startSize=0;swimlaneHead=0;swimlaneBody=0;fillColor=none;collapsible=0;dropTarget=0;points=[[0,0.5],[1,0.5]];portConstraint=eastwest;top=0;left=0;right=0;bottom=0;" value="" vertex="1">
          <mxGeometry height="30" width="200" y="185" as="geometry" />
        </mxCell>
        <mxCell id="qyUYULa52Rrzh8f9O8Ic-81" parent="qyUYULa52Rrzh8f9O8Ic-80" style="shape=partialRectangle;connectable=0;fillColor=none;top=0;left=0;bottom=0;right=0;editable=1;overflow=hidden;whiteSpace=wrap;html=1;" value="" vertex="1">
          <mxGeometry height="30" width="30" as="geometry">
            <mxRectangle height="30" width="30" as="alternateBounds" />
          </mxGeometry>
        </mxCell>
        <mxCell id="qyUYULa52Rrzh8f9O8Ic-82" parent="qyUYULa52Rrzh8f9O8Ic-80" style="shape=partialRectangle;connectable=0;fillColor=none;top=0;left=0;bottom=0;right=0;align=left;spacingLeft=6;overflow=hidden;whiteSpace=wrap;html=1;" value="&lt;span style=&quot;text-wrap: nowrap;&quot;&gt;website varchar&lt;/span&gt;" vertex="1">
          <mxGeometry height="30" width="170" x="30" as="geometry">
            <mxRectangle height="30" width="170" as="alternateBounds" />
          </mxGeometry>
        </mxCell>
        <mxCell id="qyUYULa52Rrzh8f9O8Ic-83" parent="qyUYULa52Rrzh8f9O8Ic-45" style="shape=tableRow;horizontal=0;startSize=0;swimlaneHead=0;swimlaneBody=0;fillColor=none;collapsible=0;dropTarget=0;points=[[0,0.5],[1,0.5]];portConstraint=eastwest;top=0;left=0;right=0;bottom=0;" value="" vertex="1">
          <mxGeometry height="30" width="200" y="215" as="geometry" />
        </mxCell>
        <mxCell id="qyUYULa52Rrzh8f9O8Ic-84" parent="qyUYULa52Rrzh8f9O8Ic-83" style="shape=partialRectangle;connectable=0;fillColor=none;top=0;left=0;bottom=0;right=0;editable=1;overflow=hidden;whiteSpace=wrap;html=1;" value="" vertex="1">
          <mxGeometry height="30" width="30" as="geometry">
            <mxRectangle height="30" width="30" as="alternateBounds" />
          </mxGeometry>
        </mxCell>
        <mxCell id="qyUYULa52Rrzh8f9O8Ic-85" parent="qyUYULa52Rrzh8f9O8Ic-83" style="shape=partialRectangle;connectable=0;fillColor=none;top=0;left=0;bottom=0;right=0;align=left;spacingLeft=6;overflow=hidden;whiteSpace=wrap;html=1;" value="&lt;span style=&quot;text-wrap: nowrap;&quot;&gt;opening_hours varchar&lt;/span&gt;" vertex="1">
          <mxGeometry height="30" width="170" x="30" as="geometry">
            <mxRectangle height="30" width="170" as="alternateBounds" />
          </mxGeometry>
        </mxCell>
        <mxCell id="qyUYULa52Rrzh8f9O8Ic-89" parent="1" style="shape=table;startSize=30;container=1;collapsible=1;childLayout=tableLayout;fixedRows=1;rowLines=0;fontStyle=1;align=center;resizeLast=1;html=1;" value="Pizza" vertex="1">
          <mxGeometry height="200" width="200" x="580" y="470" as="geometry" />
        </mxCell>
        <mxCell id="qyUYULa52Rrzh8f9O8Ic-90" parent="qyUYULa52Rrzh8f9O8Ic-89" style="shape=tableRow;horizontal=0;startSize=0;swimlaneHead=0;swimlaneBody=0;fillColor=none;collapsible=0;dropTarget=0;points=[[0,0.5],[1,0.5]];portConstraint=eastwest;top=0;left=0;right=0;bottom=1;" value="" vertex="1">
          <mxGeometry height="35" width="200" y="30" as="geometry" />
        </mxCell>
        <mxCell id="qyUYULa52Rrzh8f9O8Ic-91" parent="qyUYULa52Rrzh8f9O8Ic-90" style="shape=partialRectangle;connectable=0;fillColor=none;top=0;left=0;bottom=0;right=0;fontStyle=1;overflow=hidden;whiteSpace=wrap;html=1;" value="PK" vertex="1">
          <mxGeometry height="35" width="30" as="geometry">
            <mxRectangle height="35" width="30" as="alternateBounds" />
          </mxGeometry>
        </mxCell>
        <mxCell id="qyUYULa52Rrzh8f9O8Ic-92" parent="qyUYULa52Rrzh8f9O8Ic-90" style="shape=partialRectangle;connectable=0;fillColor=none;top=0;left=0;bottom=0;right=0;align=left;spacingLeft=6;fontStyle=5;overflow=hidden;whiteSpace=wrap;html=1;" value="&lt;span style=&quot;text-wrap: nowrap;&quot;&gt;Pizza_id int NOT NULL&lt;/span&gt;" vertex="1">
          <mxGeometry height="35" width="170" x="30" as="geometry">
            <mxRectangle height="35" width="170" as="alternateBounds" />
          </mxGeometry>
        </mxCell>
        <mxCell id="qyUYULa52Rrzh8f9O8Ic-93" parent="qyUYULa52Rrzh8f9O8Ic-89" style="shape=tableRow;horizontal=0;startSize=0;swimlaneHead=0;swimlaneBody=0;fillColor=none;collapsible=0;dropTarget=0;points=[[0,0.5],[1,0.5]];portConstraint=eastwest;top=0;left=0;right=0;bottom=0;" value="" vertex="1">
          <mxGeometry height="30" width="200" y="65" as="geometry" />
        </mxCell>
        <mxCell id="qyUYULa52Rrzh8f9O8Ic-94" parent="qyUYULa52Rrzh8f9O8Ic-93" style="shape=partialRectangle;connectable=0;fillColor=none;top=0;left=0;bottom=0;right=0;editable=1;overflow=hidden;whiteSpace=wrap;html=1;" value="FK" vertex="1">
          <mxGeometry height="30" width="30" as="geometry">
            <mxRectangle height="30" width="30" as="alternateBounds" />
          </mxGeometry>
        </mxCell>
        <mxCell id="qyUYULa52Rrzh8f9O8Ic-95" parent="qyUYULa52Rrzh8f9O8Ic-93" style="shape=partialRectangle;connectable=0;fillColor=none;top=0;left=0;bottom=0;right=0;align=left;spacingLeft=6;overflow=hidden;whiteSpace=wrap;html=1;" value="restaurant_id&lt;span style=&quot;text-wrap-mode: nowrap;&quot;&gt;&amp;nbsp;int&lt;/span&gt;" vertex="1">
          <mxGeometry height="30" width="170" x="30" as="geometry">
            <mxRectangle height="30" width="170" as="alternateBounds" />
          </mxGeometry>
        </mxCell>
        <mxCell id="qyUYULa52Rrzh8f9O8Ic-96" parent="qyUYULa52Rrzh8f9O8Ic-89" style="shape=tableRow;horizontal=0;startSize=0;swimlaneHead=0;swimlaneBody=0;fillColor=none;collapsible=0;dropTarget=0;points=[[0,0.5],[1,0.5]];portConstraint=eastwest;top=0;left=0;right=0;bottom=0;" value="" vertex="1">
          <mxGeometry height="30" width="200" y="95" as="geometry" />
        </mxCell>
        <mxCell id="qyUYULa52Rrzh8f9O8Ic-97" parent="qyUYULa52Rrzh8f9O8Ic-96" style="shape=partialRectangle;connectable=0;fillColor=none;top=0;left=0;bottom=0;right=0;editable=1;overflow=hidden;whiteSpace=wrap;html=1;" value="" vertex="1">
          <mxGeometry height="30" width="30" as="geometry">
            <mxRectangle height="30" width="30" as="alternateBounds" />
          </mxGeometry>
        </mxCell>
        <mxCell id="qyUYULa52Rrzh8f9O8Ic-98" parent="qyUYULa52Rrzh8f9O8Ic-96" style="shape=partialRectangle;connectable=0;fillColor=none;top=0;left=0;bottom=0;right=0;align=left;spacingLeft=6;overflow=hidden;whiteSpace=wrap;html=1;" value="&lt;span style=&quot;white-space: nowrap;&quot;&gt;name varchar&lt;/span&gt;" vertex="1">
          <mxGeometry height="30" width="170" x="30" as="geometry">
            <mxRectangle height="30" width="170" as="alternateBounds" />
          </mxGeometry>
        </mxCell>
        <mxCell id="qyUYULa52Rrzh8f9O8Ic-99" parent="qyUYULa52Rrzh8f9O8Ic-89" style="shape=tableRow;horizontal=0;startSize=0;swimlaneHead=0;swimlaneBody=0;fillColor=none;collapsible=0;dropTarget=0;points=[[0,0.5],[1,0.5]];portConstraint=eastwest;top=0;left=0;right=0;bottom=0;" value="" vertex="1">
          <mxGeometry height="30" width="200" y="125" as="geometry" />
        </mxCell>
        <mxCell id="qyUYULa52Rrzh8f9O8Ic-100" parent="qyUYULa52Rrzh8f9O8Ic-99" style="shape=partialRectangle;connectable=0;fillColor=none;top=0;left=0;bottom=0;right=0;editable=1;overflow=hidden;whiteSpace=wrap;html=1;" value="" vertex="1">
          <mxGeometry height="30" width="30" as="geometry">
            <mxRectangle height="30" width="30" as="alternateBounds" />
          </mxGeometry>
        </mxCell>
        <mxCell id="qyUYULa52Rrzh8f9O8Ic-101" parent="qyUYULa52Rrzh8f9O8Ic-99" style="shape=partialRectangle;connectable=0;fillColor=none;top=0;left=0;bottom=0;right=0;align=left;spacingLeft=6;overflow=hidden;whiteSpace=wrap;html=1;" value="&lt;span style=&quot;text-wrap: nowrap;&quot;&gt;crust_type varchar&lt;/span&gt;" vertex="1">
          <mxGeometry height="30" width="170" x="30" as="geometry">
            <mxRectangle height="30" width="170" as="alternateBounds" />
          </mxGeometry>
        </mxCell>
        <mxCell id="qyUYULa52Rrzh8f9O8Ic-105" parent="qyUYULa52Rrzh8f9O8Ic-89" style="shape=tableRow;horizontal=0;startSize=0;swimlaneHead=0;swimlaneBody=0;fillColor=none;collapsible=0;dropTarget=0;points=[[0,0.5],[1,0.5]];portConstraint=eastwest;top=0;left=0;right=0;bottom=0;" value="" vertex="1">
          <mxGeometry height="30" width="200" y="155" as="geometry" />
        </mxCell>
        <mxCell id="qyUYULa52Rrzh8f9O8Ic-106" parent="qyUYULa52Rrzh8f9O8Ic-105" style="shape=partialRectangle;connectable=0;fillColor=none;top=0;left=0;bottom=0;right=0;editable=1;overflow=hidden;whiteSpace=wrap;html=1;" value="" vertex="1">
          <mxGeometry height="30" width="30" as="geometry">
            <mxRectangle height="30" width="30" as="alternateBounds" />
          </mxGeometry>
        </mxCell>
        <mxCell id="qyUYULa52Rrzh8f9O8Ic-107" parent="qyUYULa52Rrzh8f9O8Ic-105" style="shape=partialRectangle;connectable=0;fillColor=none;top=0;left=0;bottom=0;right=0;align=left;spacingLeft=6;overflow=hidden;whiteSpace=wrap;html=1;" value="&lt;span style=&quot;white-space: nowrap;&quot;&gt;price int&lt;/span&gt;" vertex="1">
          <mxGeometry height="30" width="170" x="30" as="geometry">
            <mxRectangle height="30" width="170" as="alternateBounds" />
          </mxGeometry>
        </mxCell>
        <mxCell id="qyUYULa52Rrzh8f9O8Ic-111" parent="1" style="shape=table;startSize=30;container=1;collapsible=1;childLayout=tableLayout;fixedRows=1;rowLines=0;fontStyle=1;align=center;resizeLast=1;html=1;" value="Order" vertex="1">
          <mxGeometry height="200" width="200" x="290" y="400" as="geometry" />
        </mxCell>
        <mxCell id="qyUYULa52Rrzh8f9O8Ic-112" parent="qyUYULa52Rrzh8f9O8Ic-111" style="shape=tableRow;horizontal=0;startSize=0;swimlaneHead=0;swimlaneBody=0;fillColor=none;collapsible=0;dropTarget=0;points=[[0,0.5],[1,0.5]];portConstraint=eastwest;top=0;left=0;right=0;bottom=1;" value="" vertex="1">
          <mxGeometry height="35" width="200" y="30" as="geometry" />
        </mxCell>
        <mxCell id="qyUYULa52Rrzh8f9O8Ic-113" parent="qyUYULa52Rrzh8f9O8Ic-112" style="shape=partialRectangle;connectable=0;fillColor=none;top=0;left=0;bottom=0;right=0;fontStyle=1;overflow=hidden;whiteSpace=wrap;html=1;" value="PK" vertex="1">
          <mxGeometry height="35" width="30" as="geometry">
            <mxRectangle height="35" width="30" as="alternateBounds" />
          </mxGeometry>
        </mxCell>
        <mxCell id="qyUYULa52Rrzh8f9O8Ic-114" parent="qyUYULa52Rrzh8f9O8Ic-112" style="shape=partialRectangle;connectable=0;fillColor=none;top=0;left=0;bottom=0;right=0;align=left;spacingLeft=6;fontStyle=5;overflow=hidden;whiteSpace=wrap;html=1;" value="&lt;span style=&quot;text-wrap: nowrap;&quot;&gt;order_id int NOT NULL&lt;/span&gt;" vertex="1">
          <mxGeometry height="35" width="170" x="30" as="geometry">
            <mxRectangle height="35" width="170" as="alternateBounds" />
          </mxGeometry>
        </mxCell>
        <mxCell id="qyUYULa52Rrzh8f9O8Ic-115" parent="qyUYULa52Rrzh8f9O8Ic-111" style="shape=tableRow;horizontal=0;startSize=0;swimlaneHead=0;swimlaneBody=0;fillColor=none;collapsible=0;dropTarget=0;points=[[0,0.5],[1,0.5]];portConstraint=eastwest;top=0;left=0;right=0;bottom=0;" value="" vertex="1">
          <mxGeometry height="30" width="200" y="65" as="geometry" />
        </mxCell>
        <mxCell id="qyUYULa52Rrzh8f9O8Ic-116" parent="qyUYULa52Rrzh8f9O8Ic-115" style="shape=partialRectangle;connectable=0;fillColor=none;top=0;left=0;bottom=0;right=0;editable=1;overflow=hidden;whiteSpace=wrap;html=1;" value="" vertex="1">
          <mxGeometry height="30" width="30" as="geometry">
            <mxRectangle height="30" width="30" as="alternateBounds" />
          </mxGeometry>
        </mxCell>
        <mxCell id="qyUYULa52Rrzh8f9O8Ic-117" parent="qyUYULa52Rrzh8f9O8Ic-115" style="shape=partialRectangle;connectable=0;fillColor=none;top=0;left=0;bottom=0;right=0;align=left;spacingLeft=6;overflow=hidden;whiteSpace=wrap;html=1;" value="order_datetime&lt;span style=&quot;text-wrap-mode: nowrap;&quot;&gt;&amp;nbsp;datetime&lt;/span&gt;" vertex="1">
          <mxGeometry height="30" width="170" x="30" as="geometry">
            <mxRectangle height="30" width="170" as="alternateBounds" />
          </mxGeometry>
        </mxCell>
        <mxCell id="qyUYULa52Rrzh8f9O8Ic-118" parent="qyUYULa52Rrzh8f9O8Ic-111" style="shape=tableRow;horizontal=0;startSize=0;swimlaneHead=0;swimlaneBody=0;fillColor=none;collapsible=0;dropTarget=0;points=[[0,0.5],[1,0.5]];portConstraint=eastwest;top=0;left=0;right=0;bottom=0;" value="" vertex="1">
          <mxGeometry height="30" width="200" y="95" as="geometry" />
        </mxCell>
        <mxCell id="qyUYULa52Rrzh8f9O8Ic-119" parent="qyUYULa52Rrzh8f9O8Ic-118" style="shape=partialRectangle;connectable=0;fillColor=none;top=0;left=0;bottom=0;right=0;editable=1;overflow=hidden;whiteSpace=wrap;html=1;" value="" vertex="1">
          <mxGeometry height="30" width="30" as="geometry">
            <mxRectangle height="30" width="30" as="alternateBounds" />
          </mxGeometry>
        </mxCell>
        <mxCell id="qyUYULa52Rrzh8f9O8Ic-120" parent="qyUYULa52Rrzh8f9O8Ic-118" style="shape=partialRectangle;connectable=0;fillColor=none;top=0;left=0;bottom=0;right=0;align=left;spacingLeft=6;overflow=hidden;whiteSpace=wrap;html=1;" value="latest_delivery_time&amp;nbsp;&lt;span style=&quot;white-space: nowrap;&quot;&gt;datetime&lt;/span&gt;" vertex="1">
          <mxGeometry height="30" width="170" x="30" as="geometry">
            <mxRectangle height="30" width="170" as="alternateBounds" />
          </mxGeometry>
        </mxCell>
        <mxCell id="qyUYULa52Rrzh8f9O8Ic-121" parent="qyUYULa52Rrzh8f9O8Ic-111" style="shape=tableRow;horizontal=0;startSize=0;swimlaneHead=0;swimlaneBody=0;fillColor=none;collapsible=0;dropTarget=0;points=[[0,0.5],[1,0.5]];portConstraint=eastwest;top=0;left=0;right=0;bottom=0;" value="" vertex="1">
          <mxGeometry height="30" width="200" y="125" as="geometry" />
        </mxCell>
        <mxCell id="qyUYULa52Rrzh8f9O8Ic-122" parent="qyUYULa52Rrzh8f9O8Ic-121" style="shape=partialRectangle;connectable=0;fillColor=none;top=0;left=0;bottom=0;right=0;editable=1;overflow=hidden;whiteSpace=wrap;html=1;" value="" vertex="1">
          <mxGeometry height="30" width="30" as="geometry">
            <mxRectangle height="30" width="30" as="alternateBounds" />
          </mxGeometry>
        </mxCell>
        <mxCell id="qyUYULa52Rrzh8f9O8Ic-123" parent="qyUYULa52Rrzh8f9O8Ic-121" style="shape=partialRectangle;connectable=0;fillColor=none;top=0;left=0;bottom=0;right=0;align=left;spacingLeft=6;overflow=hidden;whiteSpace=wrap;html=1;" value="&lt;span style=&quot;text-wrap: nowrap;&quot;&gt;num_people int&lt;/span&gt;" vertex="1">
          <mxGeometry height="30" width="170" x="30" as="geometry">
            <mxRectangle height="30" width="170" as="alternateBounds" />
          </mxGeometry>
        </mxCell>
        <mxCell id="qyUYULa52Rrzh8f9O8Ic-124" parent="qyUYULa52Rrzh8f9O8Ic-111" style="shape=tableRow;horizontal=0;startSize=0;swimlaneHead=0;swimlaneBody=0;fillColor=none;collapsible=0;dropTarget=0;points=[[0,0.5],[1,0.5]];portConstraint=eastwest;top=0;left=0;right=0;bottom=0;" value="" vertex="1">
          <mxGeometry height="30" width="200" y="155" as="geometry" />
        </mxCell>
        <mxCell id="qyUYULa52Rrzh8f9O8Ic-125" parent="qyUYULa52Rrzh8f9O8Ic-124" style="shape=partialRectangle;connectable=0;fillColor=none;top=0;left=0;bottom=0;right=0;editable=1;overflow=hidden;whiteSpace=wrap;html=1;" value="FK" vertex="1">
          <mxGeometry height="30" width="30" as="geometry">
            <mxRectangle height="30" width="30" as="alternateBounds" />
          </mxGeometry>
        </mxCell>
        <mxCell id="qyUYULa52Rrzh8f9O8Ic-126" parent="qyUYULa52Rrzh8f9O8Ic-124" style="shape=partialRectangle;connectable=0;fillColor=none;top=0;left=0;bottom=0;right=0;align=left;spacingLeft=6;overflow=hidden;whiteSpace=wrap;html=1;" value="customer_id&amp;nbsp;&lt;span style=&quot;white-space: nowrap;&quot;&gt;int&lt;/span&gt;" vertex="1">
          <mxGeometry height="30" width="170" x="30" as="geometry">
            <mxRectangle height="30" width="170" as="alternateBounds" />
          </mxGeometry>
        </mxCell>
        <mxCell id="qyUYULa52Rrzh8f9O8Ic-127" parent="1" style="shape=table;startSize=30;container=1;collapsible=1;childLayout=tableLayout;fixedRows=1;rowLines=0;fontStyle=1;align=center;resizeLast=1;html=1;" value="Entertainment Order" vertex="1">
          <mxGeometry height="170" width="200" x="20" y="510" as="geometry" />
        </mxCell>
        <mxCell id="qyUYULa52Rrzh8f9O8Ic-128" parent="qyUYULa52Rrzh8f9O8Ic-127" style="shape=tableRow;horizontal=0;startSize=0;swimlaneHead=0;swimlaneBody=0;fillColor=none;collapsible=0;dropTarget=0;points=[[0,0.5],[1,0.5]];portConstraint=eastwest;top=0;left=0;right=0;bottom=1;" value="" vertex="1">
          <mxGeometry height="35" width="200" y="30" as="geometry" />
        </mxCell>
        <mxCell id="qyUYULa52Rrzh8f9O8Ic-129" parent="qyUYULa52Rrzh8f9O8Ic-128" style="shape=partialRectangle;connectable=0;fillColor=none;top=0;left=0;bottom=0;right=0;fontStyle=1;overflow=hidden;whiteSpace=wrap;html=1;" value="PK" vertex="1">
          <mxGeometry height="35" width="30" as="geometry">
            <mxRectangle height="35" width="30" as="alternateBounds" />
          </mxGeometry>
        </mxCell>
        <mxCell id="qyUYULa52Rrzh8f9O8Ic-130" parent="qyUYULa52Rrzh8f9O8Ic-128" style="shape=partialRectangle;connectable=0;fillColor=none;top=0;left=0;bottom=0;right=0;align=left;spacingLeft=6;fontStyle=5;overflow=hidden;whiteSpace=wrap;html=1;" value="&lt;span style=&quot;text-wrap: nowrap;&quot;&gt;eorder_id int NOT NULL&lt;/span&gt;" vertex="1">
          <mxGeometry height="35" width="170" x="30" as="geometry">
            <mxRectangle height="35" width="170" as="alternateBounds" />
          </mxGeometry>
        </mxCell>
        <mxCell id="qyUYULa52Rrzh8f9O8Ic-131" parent="qyUYULa52Rrzh8f9O8Ic-127" style="shape=tableRow;horizontal=0;startSize=0;swimlaneHead=0;swimlaneBody=0;fillColor=none;collapsible=0;dropTarget=0;points=[[0,0.5],[1,0.5]];portConstraint=eastwest;top=0;left=0;right=0;bottom=0;" value="" vertex="1">
          <mxGeometry height="30" width="200" y="65" as="geometry" />
        </mxCell>
        <mxCell id="qyUYULa52Rrzh8f9O8Ic-132" parent="qyUYULa52Rrzh8f9O8Ic-131" style="shape=partialRectangle;connectable=0;fillColor=none;top=0;left=0;bottom=0;right=0;editable=1;overflow=hidden;whiteSpace=wrap;html=1;" value="FK" vertex="1">
          <mxGeometry height="30" width="30" as="geometry">
            <mxRectangle height="30" width="30" as="alternateBounds" />
          </mxGeometry>
        </mxCell>
        <mxCell id="qyUYULa52Rrzh8f9O8Ic-133" parent="qyUYULa52Rrzh8f9O8Ic-131" style="shape=partialRectangle;connectable=0;fillColor=none;top=0;left=0;bottom=0;right=0;align=left;spacingLeft=6;overflow=hidden;whiteSpace=wrap;html=1;" value="entertainer_id&lt;span style=&quot;text-wrap-mode: nowrap;&quot;&gt;&amp;nbsp;int&lt;/span&gt;" vertex="1">
          <mxGeometry height="30" width="170" x="30" as="geometry">
            <mxRectangle height="30" width="170" as="alternateBounds" />
          </mxGeometry>
        </mxCell>
        <mxCell id="qyUYULa52Rrzh8f9O8Ic-134" parent="qyUYULa52Rrzh8f9O8Ic-127" style="shape=tableRow;horizontal=0;startSize=0;swimlaneHead=0;swimlaneBody=0;fillColor=none;collapsible=0;dropTarget=0;points=[[0,0.5],[1,0.5]];portConstraint=eastwest;top=0;left=0;right=0;bottom=0;" value="" vertex="1">
          <mxGeometry height="30" width="200" y="95" as="geometry" />
        </mxCell>
        <mxCell id="qyUYULa52Rrzh8f9O8Ic-135" parent="qyUYULa52Rrzh8f9O8Ic-134" style="shape=partialRectangle;connectable=0;fillColor=none;top=0;left=0;bottom=0;right=0;editable=1;overflow=hidden;whiteSpace=wrap;html=1;" value="" vertex="1">
          <mxGeometry height="30" width="30" as="geometry">
            <mxRectangle height="30" width="30" as="alternateBounds" />
          </mxGeometry>
        </mxCell>
        <mxCell id="qyUYULa52Rrzh8f9O8Ic-136" parent="qyUYULa52Rrzh8f9O8Ic-134" style="shape=partialRectangle;connectable=0;fillColor=none;top=0;left=0;bottom=0;right=0;align=left;spacingLeft=6;overflow=hidden;whiteSpace=wrap;html=1;" value="&lt;span style=&quot;text-wrap: nowrap;&quot;&gt;entertainment_type varchar&lt;/span&gt;" vertex="1">
          <mxGeometry height="30" width="170" x="30" as="geometry">
            <mxRectangle height="30" width="170" as="alternateBounds" />
          </mxGeometry>
        </mxCell>
        <mxCell id="qyUYULa52Rrzh8f9O8Ic-140" parent="qyUYULa52Rrzh8f9O8Ic-127" style="shape=tableRow;horizontal=0;startSize=0;swimlaneHead=0;swimlaneBody=0;fillColor=none;collapsible=0;dropTarget=0;points=[[0,0.5],[1,0.5]];portConstraint=eastwest;top=0;left=0;right=0;bottom=0;" value="" vertex="1">
          <mxGeometry height="30" width="200" y="125" as="geometry" />
        </mxCell>
        <mxCell id="qyUYULa52Rrzh8f9O8Ic-141" parent="qyUYULa52Rrzh8f9O8Ic-140" style="shape=partialRectangle;connectable=0;fillColor=none;top=0;left=0;bottom=0;right=0;editable=1;overflow=hidden;whiteSpace=wrap;html=1;" value="" vertex="1">
          <mxGeometry height="30" width="30" as="geometry">
            <mxRectangle height="30" width="30" as="alternateBounds" />
          </mxGeometry>
        </mxCell>
        <mxCell id="qyUYULa52Rrzh8f9O8Ic-142" parent="qyUYULa52Rrzh8f9O8Ic-140" style="shape=partialRectangle;connectable=0;fillColor=none;top=0;left=0;bottom=0;right=0;align=left;spacingLeft=6;overflow=hidden;whiteSpace=wrap;html=1;" value="&lt;span style=&quot;text-wrap: nowrap;&quot;&gt;duration int&lt;/span&gt;" vertex="1">
          <mxGeometry height="30" width="170" x="30" as="geometry">
            <mxRectangle height="30" width="170" as="alternateBounds" />
          </mxGeometry>
        </mxCell>
        <mxCell id="qyUYULa52Rrzh8f9O8Ic-159" parent="1" style="shape=table;startSize=30;container=1;collapsible=1;childLayout=tableLayout;fixedRows=1;rowLines=0;fontStyle=1;align=center;resizeLast=1;html=1;" value="Availability" vertex="1">
          <mxGeometry height="175" width="200" x="300" y="640" as="geometry" />
        </mxCell>
        <mxCell id="qyUYULa52Rrzh8f9O8Ic-160" parent="qyUYULa52Rrzh8f9O8Ic-159" style="shape=tableRow;horizontal=0;startSize=0;swimlaneHead=0;swimlaneBody=0;fillColor=none;collapsible=0;dropTarget=0;points=[[0,0.5],[1,0.5]];portConstraint=eastwest;top=0;left=0;right=0;bottom=1;" value="" vertex="1">
          <mxGeometry height="35" width="200" y="30" as="geometry" />
        </mxCell>
        <mxCell id="qyUYULa52Rrzh8f9O8Ic-161" parent="qyUYULa52Rrzh8f9O8Ic-160" style="shape=partialRectangle;connectable=0;fillColor=none;top=0;left=0;bottom=0;right=0;fontStyle=1;overflow=hidden;whiteSpace=wrap;html=1;" value="PK" vertex="1">
          <mxGeometry height="35" width="30" as="geometry">
            <mxRectangle height="35" width="30" as="alternateBounds" />
          </mxGeometry>
        </mxCell>
        <mxCell id="qyUYULa52Rrzh8f9O8Ic-162" parent="qyUYULa52Rrzh8f9O8Ic-160" style="shape=partialRectangle;connectable=0;fillColor=none;top=0;left=0;bottom=0;right=0;align=left;spacingLeft=6;fontStyle=5;overflow=hidden;whiteSpace=wrap;html=1;" value="&lt;span style=&quot;text-wrap: nowrap;&quot;&gt;avaibility_id int NOT NULL&lt;/span&gt;" vertex="1">
          <mxGeometry height="35" width="170" x="30" as="geometry">
            <mxRectangle height="35" width="170" as="alternateBounds" />
          </mxGeometry>
        </mxCell>
        <mxCell id="qyUYULa52Rrzh8f9O8Ic-163" parent="qyUYULa52Rrzh8f9O8Ic-159" style="shape=tableRow;horizontal=0;startSize=0;swimlaneHead=0;swimlaneBody=0;fillColor=none;collapsible=0;dropTarget=0;points=[[0,0.5],[1,0.5]];portConstraint=eastwest;top=0;left=0;right=0;bottom=0;" value="" vertex="1">
          <mxGeometry height="30" width="200" y="65" as="geometry" />
        </mxCell>
        <mxCell id="qyUYULa52Rrzh8f9O8Ic-164" parent="qyUYULa52Rrzh8f9O8Ic-163" style="shape=partialRectangle;connectable=0;fillColor=none;top=0;left=0;bottom=0;right=0;editable=1;overflow=hidden;whiteSpace=wrap;html=1;" value="FK" vertex="1">
          <mxGeometry height="30" width="30" as="geometry">
            <mxRectangle height="30" width="30" as="alternateBounds" />
          </mxGeometry>
        </mxCell>
        <mxCell id="qyUYULa52Rrzh8f9O8Ic-165" parent="qyUYULa52Rrzh8f9O8Ic-163" style="shape=partialRectangle;connectable=0;fillColor=none;top=0;left=0;bottom=0;right=0;align=left;spacingLeft=6;overflow=hidden;whiteSpace=wrap;html=1;" value="entertainer_id &lt;span style=&quot;white-space: nowrap;&quot;&gt;int&lt;/span&gt;" vertex="1">
          <mxGeometry height="30" width="170" x="30" as="geometry">
            <mxRectangle height="30" width="170" as="alternateBounds" />
          </mxGeometry>
        </mxCell>
        <mxCell id="qyUYULa52Rrzh8f9O8Ic-166" parent="qyUYULa52Rrzh8f9O8Ic-159" style="shape=tableRow;horizontal=0;startSize=0;swimlaneHead=0;swimlaneBody=0;fillColor=none;collapsible=0;dropTarget=0;points=[[0,0.5],[1,0.5]];portConstraint=eastwest;top=0;left=0;right=0;bottom=0;" value="" vertex="1">
          <mxGeometry height="35" width="200" y="95" as="geometry" />
        </mxCell>
        <mxCell id="qyUYULa52Rrzh8f9O8Ic-167" parent="qyUYULa52Rrzh8f9O8Ic-166" style="shape=partialRectangle;connectable=0;fillColor=none;top=0;left=0;bottom=0;right=0;editable=1;overflow=hidden;whiteSpace=wrap;html=1;" value="FK" vertex="1">
          <mxGeometry height="35" width="30" as="geometry">
            <mxRectangle height="35" width="30" as="alternateBounds" />
          </mxGeometry>
        </mxCell>
        <mxCell id="qyUYULa52Rrzh8f9O8Ic-168" parent="qyUYULa52Rrzh8f9O8Ic-166" style="shape=partialRectangle;connectable=0;fillColor=none;top=0;left=0;bottom=0;right=0;align=left;spacingLeft=6;overflow=hidden;whiteSpace=wrap;html=1;" value="&lt;span style=&quot;text-wrap: nowrap;&quot;&gt;restaurant_id int&lt;/span&gt;" vertex="1">
          <mxGeometry height="35" width="170" x="30" as="geometry">
            <mxRectangle height="35" width="170" as="alternateBounds" />
          </mxGeometry>
        </mxCell>
        <mxCell id="qyUYULa52Rrzh8f9O8Ic-169" parent="qyUYULa52Rrzh8f9O8Ic-159" style="shape=tableRow;horizontal=0;startSize=0;swimlaneHead=0;swimlaneBody=0;fillColor=none;collapsible=0;dropTarget=0;points=[[0,0.5],[1,0.5]];portConstraint=eastwest;top=0;left=0;right=0;bottom=0;" value="" vertex="1">
          <mxGeometry height="30" width="200" y="130" as="geometry" />
        </mxCell>
        <mxCell id="qyUYULa52Rrzh8f9O8Ic-170" parent="qyUYULa52Rrzh8f9O8Ic-169" style="shape=partialRectangle;connectable=0;fillColor=none;top=0;left=0;bottom=0;right=0;editable=1;overflow=hidden;whiteSpace=wrap;html=1;" value="" vertex="1">
          <mxGeometry height="30" width="30" as="geometry">
            <mxRectangle height="30" width="30" as="alternateBounds" />
          </mxGeometry>
        </mxCell>
        <mxCell id="qyUYULa52Rrzh8f9O8Ic-171" parent="qyUYULa52Rrzh8f9O8Ic-169" style="shape=partialRectangle;connectable=0;fillColor=none;top=0;left=0;bottom=0;right=0;align=left;spacingLeft=6;overflow=hidden;whiteSpace=wrap;html=1;" value="day_of_week varchar" vertex="1">
          <mxGeometry height="30" width="170" x="30" as="geometry">
            <mxRectangle height="30" width="170" as="alternateBounds" />
          </mxGeometry>
        </mxCell>
        <mxCell id="qyUYULa52Rrzh8f9O8Ic-173" edge="1" parent="1" source="qyUYULa52Rrzh8f9O8Ic-9" style="edgeStyle=entityRelationEdgeStyle;fontSize=12;html=1;endArrow=ERoneToMany;rounded=0;exitX=1;exitY=0.5;exitDx=0;exitDy=0;entryX=0;entryY=0.5;entryDx=0;entryDy=0;" target="qyUYULa52Rrzh8f9O8Ic-52" value="">
          <mxGeometry height="100" relative="1" width="100" as="geometry">
            <mxPoint x="580" y="280" as="sourcePoint" />
            <mxPoint x="680" y="180" as="targetPoint" />
          </mxGeometry>
        </mxCell>
        <mxCell id="qyUYULa52Rrzh8f9O8Ic-174" edge="1" parent="1" style="edgeStyle=entityRelationEdgeStyle;fontSize=12;html=1;endArrow=ERmandOne;startArrow=ERmandOne;rounded=0;entryX=0;entryY=0.5;entryDx=0;entryDy=0;" target="qyUYULa52Rrzh8f9O8Ic-9" value="">
          <mxGeometry height="100" relative="1" width="100" as="geometry">
            <mxPoint x="220" y="150" as="sourcePoint" />
            <mxPoint x="260" y="130" as="targetPoint" />
          </mxGeometry>
        </mxCell>
        <mxCell id="qyUYULa52Rrzh8f9O8Ic-175" edge="1" parent="1" source="qyUYULa52Rrzh8f9O8Ic-1" style="edgeStyle=entityRelationEdgeStyle;fontSize=12;html=1;endArrow=ERmandOne;startArrow=ERmandOne;rounded=0;entryX=-0.003;entryY=0.13;entryDx=0;entryDy=0;entryPerimeter=0;exitX=1;exitY=0.211;exitDx=0;exitDy=0;exitPerimeter=0;" target="qyUYULa52Rrzh8f9O8Ic-18" value="">
          <mxGeometry height="100" relative="1" width="100" as="geometry">
            <mxPoint x="220" y="200" as="sourcePoint" />
            <mxPoint x="260" y="202" as="targetPoint" />
          </mxGeometry>
        </mxCell>
        <mxCell id="qyUYULa52Rrzh8f9O8Ic-176" edge="1" parent="1" style="edgeStyle=entityRelationEdgeStyle;fontSize=12;html=1;endArrow=ERmandOne;startArrow=ERmandOne;rounded=0;" target="qyUYULa52Rrzh8f9O8Ic-29" value="">
          <mxGeometry height="100" relative="1" width="100" as="geometry">
            <mxPoint x="220" y="210" as="sourcePoint" />
            <mxPoint x="190" y="222" as="targetPoint" />
          </mxGeometry>
        </mxCell>
        <mxCell id="qyUYULa52Rrzh8f9O8Ic-177" edge="1" parent="1" source="qyUYULa52Rrzh8f9O8Ic-83" style="edgeStyle=entityRelationEdgeStyle;fontSize=12;html=1;endArrow=ERoneToMany;rounded=0;exitX=1;exitY=0.5;exitDx=0;exitDy=0;" target="qyUYULa52Rrzh8f9O8Ic-93" value="">
          <mxGeometry height="100" relative="1" width="100" as="geometry">
            <mxPoint x="580" y="390" as="sourcePoint" />
            <mxPoint x="680" y="290" as="targetPoint" />
          </mxGeometry>
        </mxCell>
        <mxCell id="qyUYULa52Rrzh8f9O8Ic-178" edge="1" parent="1" source="qyUYULa52Rrzh8f9O8Ic-18" style="edgeStyle=entityRelationEdgeStyle;fontSize=12;html=1;endArrow=ERoneToMany;rounded=0;exitX=0.5;exitY=1;exitDx=0;exitDy=0;entryX=0.5;entryY=0;entryDx=0;entryDy=0;" target="qyUYULa52Rrzh8f9O8Ic-111" value="">
          <mxGeometry height="100" relative="1" width="100" as="geometry">
            <mxPoint x="790" y="300" as="sourcePoint" />
            <mxPoint x="790" y="455" as="targetPoint" />
          </mxGeometry>
        </mxCell>
        <mxCell id="qyUYULa52Rrzh8f9O8Ic-179" edge="1" parent="1" source="qyUYULa52Rrzh8f9O8Ic-22" style="edgeStyle=orthogonalEdgeStyle;fontSize=12;html=1;endArrow=ERoneToMany;rounded=1;exitX=0;exitY=0.5;exitDx=0;exitDy=0;entryX=0;entryY=0.5;entryDx=0;entryDy=0;" target="qyUYULa52Rrzh8f9O8Ic-115" value="">
          <mxGeometry height="100" relative="1" width="100" as="geometry">
            <Array as="points">
              <mxPoint x="260" y="300" />
              <mxPoint x="260" y="480" />
            </Array>
            <mxPoint x="270" y="380" as="sourcePoint" />
            <mxPoint x="270" y="420" as="targetPoint" />
          </mxGeometry>
        </mxCell>
        <mxCell id="qyUYULa52Rrzh8f9O8Ic-180" edge="1" parent="1" source="qyUYULa52Rrzh8f9O8Ic-112" style="edgeStyle=entityRelationEdgeStyle;fontSize=12;html=1;endArrow=ERmany;startArrow=ERmany;rounded=0;exitX=1;exitY=0.5;exitDx=0;exitDy=0;entryX=-0.004;entryY=0.049;entryDx=0;entryDy=0;entryPerimeter=0;" target="qyUYULa52Rrzh8f9O8Ic-89" value="">
          <mxGeometry height="100" relative="1" width="100" as="geometry">
            <mxPoint x="580" y="600" as="sourcePoint" />
            <mxPoint x="680" y="500" as="targetPoint" />
          </mxGeometry>
        </mxCell>
        <mxCell id="qyUYULa52Rrzh8f9O8Ic-181" edge="1" parent="1" source="qyUYULa52Rrzh8f9O8Ic-127" style="edgeStyle=entityRelationEdgeStyle;fontSize=12;html=1;endArrow=ERmandOne;startArrow=ERmandOne;rounded=0;exitX=0.997;exitY=0.116;exitDx=0;exitDy=0;exitPerimeter=0;" value="">
          <mxGeometry height="100" relative="1" width="100" as="geometry">
            <mxPoint x="580" y="600" as="sourcePoint" />
            <mxPoint x="290" y="510" as="targetPoint" />
          </mxGeometry>
        </mxCell>
        <mxCell id="qyUYULa52Rrzh8f9O8Ic-182" edge="1" parent="1" source="qyUYULa52Rrzh8f9O8Ic-28" style="fontSize=12;html=1;endArrow=ERoneToMany;rounded=0;exitX=0.5;exitY=1;exitDx=0;exitDy=0;entryX=0.5;entryY=0;entryDx=0;entryDy=0;" target="qyUYULa52Rrzh8f9O8Ic-127" value="">
          <mxGeometry height="100" relative="1" width="100" as="geometry">
            <mxPoint x="580" y="600" as="sourcePoint" />
            <mxPoint x="680" y="500" as="targetPoint" />
          </mxGeometry>
        </mxCell>
        <mxCell id="qyUYULa52Rrzh8f9O8Ic-183" edge="1" parent="1" style="edgeStyle=entityRelationEdgeStyle;fontSize=12;html=1;endArrow=ERmany;startArrow=ERmany;rounded=0;entryX=-0.008;entryY=0.774;entryDx=0;entryDy=0;entryPerimeter=0;" target="qyUYULa52Rrzh8f9O8Ic-160" value="">
          <mxGeometry height="100" relative="1" width="100" as="geometry">
            <mxPoint x="220" y="450" as="sourcePoint" />
            <mxPoint x="680" y="500" as="targetPoint" />
          </mxGeometry>
        </mxCell>
        <mxCell id="qyUYULa52Rrzh8f9O8Ic-185" edge="1" parent="1" source="qyUYULa52Rrzh8f9O8Ic-159" style="fontSize=12;html=1;endArrow=ERmany;startArrow=ERmany;rounded=0;exitX=0.924;exitY=0.002;exitDx=0;exitDy=0;entryX=0.5;entryY=1;entryDx=0;entryDy=0;exitPerimeter=0;" target="qyUYULa52Rrzh8f9O8Ic-45" value="">
          <mxGeometry height="100" relative="1" width="100" as="geometry">
            <mxPoint x="580" y="600" as="sourcePoint" />
            <mxPoint x="680" y="500" as="targetPoint" />
          </mxGeometry>
        </mxCell>
      </root>
    </mxGraphModel>
  </diagram>
</mxfile>
